reactome2py/__init__.py
reactome2py/analysis.py
reactome2py/content.py
reactome2py/fiviz.py
reactome2py/utils.py
reactome2py-3.0.0.dist-info/LICENSE
reactome2py-3.0.0.dist-info/METADATA
reactome2py-3.0.0.dist-info/WHEEL
reactome2py-3.0.0.dist-info/entry_points.txt
reactome2py-3.0.0.dist-info/top_level.txt
reactome2py-3.0.0.dist-info/RECORD
