Metadata-Version: 2.1
Name: reactome2py
Version: 3.0.0
Summary: Python client for Reactome content and analysis service API calls.
Home-page: https://github.com/reactome/reactome2py
Author: Nasim Sanati
Author-email: nasim@plenary.org
License: Apache
Platform: any
Classifier: Programming Language :: Python
Classifier: Programming Language :: Python :: 3.6
Classifier: Programming Language :: Python :: 3.7
Classifier: Programming Language :: Python :: 3.8
Classifier: License :: OSI Approved :: Apache Software License
Classifier: Intended Audience :: Developers
Classifier: Intended Audience :: Science/Research
Classifier: License :: OSI Approved :: Apache Software License
Classifier: Topic :: Software Development :: Libraries
Classifier: Topic :: Scientific/Engineering
Classifier: Topic :: Scientific/Engineering :: Bio-Informatics
Requires-Python: >=3.6
Requires-Dist: requests
Requires-Dist: pandas (>=0.24.2)
Requires-Dist: json5 (>=0.8.4)
